{
    "os": "macOS-12.4-arm64-arm-64bit",
    "python": "3.10.5",
    "heartbeatAt": "2022-07-04T01:01:21.116549",
    "startedAt": "2022-07-04T01:01:20.378686",
    "docker": null,
    "cpu_count": 8,
    "cuda": null,
    "args": [
        "--model",
        "cox",
        "--dataset",
        "test",
        "--alpha=0.0054125078046136695",
        "--seed=572025"
    ],
    "state": "running",
    "program": "/Users/jahan/Documents/cardiacdeepsurv/train.py",
    "codePath": "train.py",
    "host": "jahans-MacBook-Air.local",
    "username": "jahan",
    "executable": "/opt/homebrew/Caskroom/miniconda/base/envs/surv/bin/python"
}
